BnFeatureExtraction/__init__.py
BnFeatureExtraction/kalpurush.ttf
BnFeatureExtraction-0.3.dist-info/LICENSE
BnFeatureExtraction-0.3.dist-info/METADATA
BnFeatureExtraction-0.3.dist-info/WHEEL
BnFeatureExtraction-0.3.dist-info/top_level.txt
BnFeatureExtraction-0.3.dist-info/RECORD
